pyspark_data_mocker/__init__.py
pyspark_data_mocker/config/__init__.py
pyspark_data_mocker/config/app_config.py
pyspark_data_mocker/config/default_config.yaml
pyspark_data_mocker/config/schema.py
pyspark_data_mocker/config/validators.py
pyspark_data_mocker/datalake_builder.py
pyspark_data_mocker/spark_session.py
pyspark_data_mocker/utils.py
pyspark_data_mocker-4.0.0.dist-info/LICENSE
pyspark_data_mocker-4.0.0.dist-info/METADATA
pyspark_data_mocker-4.0.0.dist-info/WHEEL
pyspark_data_mocker-4.0.0.dist-info/RECORD
