Metadata-Version: 2.1
Name: pyspark-data-mocker
Version: 4.0.0
Summary: Mock a datalake easily to be able to test your pyspark data application
Home-page: https://fedemgp.github.io
License: GPL-3.0
Keywords: pyspark,tests,data,mocker
Author: Federico Gomez
Author-email: fedemgp@gmail.com
Requires-Python: >=3.8,<4.0
Classifier: License :: OSI Approved :: GNU General Public License v3 (GPLv3)
Classifier: Programming Language :: Python :: 3
Classifier: Programming Language :: Python :: 3.8
Classifier: Programming Language :: Python :: 3.9
Classifier: Programming Language :: Python :: 3.10
Classifier: Programming Language :: Python :: 3.11
Requires-Dist: dacite (>=1.8.1,<2.0.0)
Requires-Dist: pyspark (>=3.2.1,<4.0.0)
Requires-Dist: pyyaml (>=6.0.1,<7.0.0)
Requires-Dist: schema (==0.7.5)
Project-URL: Repository, https://github.com/fedemgp/pyspark_data_mocker/
